upstash_search/__init__.py
upstash_search/asyncio/__init__.py
upstash_search/asyncio/http.py
upstash_search/asyncio/index.py
upstash_search/asyncio/search.py
upstash_search/errors.py
upstash_search/http.py
upstash_search/index.py
upstash_search/paths.py
upstash_search/py.typed
upstash_search/search.py
upstash_search/types.py
upstash_search/utils.py
upstash_search-0.1.1.dist-info/LICENSE
upstash_search-0.1.1.dist-info/METADATA
upstash_search-0.1.1.dist-info/WHEEL
upstash_search-0.1.1.dist-info/RECORD
