Metadata-Version: 2.1
Name: upstash-search
Version: 0.1.1
Summary: An HTTP/REST based AI Search client built on top of Upstash REST API.
Home-page: https://github.com/upstash/search-py
License: MIT
Keywords: Search,Upstash Search,Serverless Search
Author: Upstash
Author-email: support@upstash.com
Maintainer: Upstash
Maintainer-email: support@upstash.com
Requires-Python: >=3.9,<4.0
Classifier: Development Status :: 5 - Production/Stable
Classifier: Intended Audience :: Developers
Classifier: License :: OSI Approved :: MIT License
Classifier: Operating System :: OS Independent
Classifier: Programming Language :: Python
Classifier: Programming Language :: Python :: 3
Classifier: Programming Language :: Python :: 3.9
Classifier: Programming Language :: Python :: 3.10
Classifier: Programming Language :: Python :: 3.11
Classifier: Programming Language :: Python :: 3.12
Classifier: Programming Language :: Python :: 3.13
Classifier: Programming Language :: Python :: 3 :: Only
Classifier: Programming Language :: Python :: Implementation :: CPython
Classifier: Topic :: Database
Classifier: Topic :: Database :: Front-Ends
Classifier: Topic :: Software Development :: Libraries
Requires-Dist: httpx (>=0.23.0,<1)
Project-URL: Repository, https://github.com/upstash/search-py
